eykenglish/__init__.py
eykenglish/eykenglish.py
eykenglish/eykmath.py
eykenglish/unicodelib.py
eykenglish-0.0.1b0.dist-info/licenses/LICENSE.md
eykenglish-0.0.1b0.dist-info/METADATA
eykenglish-0.0.1b0.dist-info/WHEEL
eykenglish-0.0.1b0.dist-info/top_level.txt
eykenglish-0.0.1b0.dist-info/RECORD
