Metadata-Version: 2.4
Name: eykenglish
Version: 0.0.1b0
Summary: A crash-proof utility library designed for maximum speed and simplicity, using deliberate thread-unsafe global state for performance. (CC BY-ND 4.0 license).
License-Expression: CC-BY-ND-4.0
Keywords: english,language,nlp,eyk,utility,crash-proof,thread-unsafe,cc-by-nd,danger,speed
Classifier: Development Status :: 4 - Beta
Classifier: Operating System :: OS Independent
Classifier: Intended Audience :: Developers
Classifier: Topic :: Software Development :: Libraries :: Python Modules
Classifier: Natural Language :: English
Classifier: Programming Language :: Python :: 3
Classifier: Programming Language :: Python :: 3 :: Only
Classifier: Programming Language :: Python :: 3.6
Classifier: Programming Language :: Python :: 3.7
Classifier: Programming Language :: Python :: 3.8
Classifier: Programming Language :: Python :: 3.9
Classifier: Programming Language :: Python :: 3.10
Classifier: Programming Language :: Python :: 3.11
Classifier: Programming Language :: Python :: 3.12
Classifier: Programming Language :: Python :: 3.13
Requires-Python: >=3.6
License-File: LICENSE.md
Dynamic: license-file
